{
    "m_Version": 12,
    "DisplayName": "#STR_EXPANSION_MARKET_CATEGORY_AMMOBOXES",
    "Icon": "Deliver",
    "Color": "FBFCFEFF",
    "IsExchange": 0,
    "InitStockPercent": 75.0,
    "Items": [
        {
            "ClassName": "ammobox_00buck_10rnd",
            "MaxPriceThreshold": 300,
            "MinPriceThreshold": 270,
            "SellPricePercent": -1.0,
            "MaxStockThreshold": 1,
            "MinStockThreshold": 1,
            "QuantityPercent": -1,
            "SpawnAttachments": [],
            "Variants": []
        },
        {
            "ClassName": "ammobox_12gaslug_10rnd",
            "MaxPriceThreshold": 300,
            "MinPriceThreshold": 270,
            "SellPricePercent": -1.0,
            "MaxStockThreshold": 1,
            "MinStockThreshold": 1,
            "QuantityPercent": -1,
            "SpawnAttachments": [],
            "Variants": []
        },
        {
            "ClassName": "ammobox_12garubberslug_10rnd",
            "MaxPriceThreshold": 240,
            "MinPriceThreshold": 216,
            "SellPricePercent": -1.0,
            "MaxStockThreshold": 1,
            "MinStockThreshold": 1,
            "QuantityPercent": -1,
            "SpawnAttachments": [],
            "Variants": []
        },
        {
            "ClassName": "ammobox_22_50rnd",
            "MaxPriceThreshold": 500,
            "MinPriceThreshold": 450,
            "SellPricePercent": -1.0,
            "MaxStockThreshold": 1,
            "MinStockThreshold": 1,
            "QuantityPercent": -1,
            "SpawnAttachments": [],
            "Variants": []
        },
        {
            "ClassName": "ammobox_308win_20rnd",
            "MaxPriceThreshold": 1100,
            "MinPriceThreshold": 990,
            "SellPricePercent": -1.0,
            "MaxStockThreshold": 1,
            "MinStockThreshold": 1,
            "QuantityPercent": -1,
            "SpawnAttachments": [],
            "Variants": [
                "ammobox_308wintracer_20rnd"
            ]
        },
        {
            "ClassName": "ammobox_308wintracer_20rnd",
            "MaxPriceThreshold": 1300,
            "MinPriceThreshold": 1170,
            "SellPricePercent": -1.0,
            "MaxStockThreshold": 1,
            "MinStockThreshold": 1,
            "QuantityPercent": -1,
            "SpawnAttachments": [],
            "Variants": []
        },
        {
            "ClassName": "ammobox_357_20rnd",
            "MaxPriceThreshold": 600,
            "MinPriceThreshold": 540,
            "SellPricePercent": -1.0,
            "MaxStockThreshold": 1,
            "MinStockThreshold": 1,
            "QuantityPercent": -1,
            "SpawnAttachments": [],
            "Variants": []
        },
        {
            "ClassName": "ammobox_380_35rnd",
            "MaxPriceThreshold": 770,
            "MinPriceThreshold": 693,
            "SellPricePercent": -1.0,
            "MaxStockThreshold": 1,
            "MinStockThreshold": 1,
            "QuantityPercent": -1,
            "SpawnAttachments": [],
            "Variants": []
        },
        {
            "ClassName": "ammobox_45acp_25rnd",
            "MaxPriceThreshold": 625,
            "MinPriceThreshold": 562,
            "SellPricePercent": -1.0,
            "MaxStockThreshold": 1,
            "MinStockThreshold": 1,
            "QuantityPercent": -1,
            "SpawnAttachments": [],
            "Variants": []
        },
        {
            "ClassName": "ammobox_545x39_20rnd",
            "MaxPriceThreshold": 960,
            "MinPriceThreshold": 864,
            "SellPricePercent": -1.0,
            "MaxStockThreshold": 1,
            "MinStockThreshold": 1,
            "QuantityPercent": -1,
            "SpawnAttachments": [],
            "Variants": [
                "ammobox_545x39tracer_20rnd"
            ]
        },
        {
            "ClassName": "ammobox_545x39tracer_20rnd",
            "MaxPriceThreshold": 1100,
            "MinPriceThreshold": 990,
            "SellPricePercent": -1.0,
            "MaxStockThreshold": 1,
            "MinStockThreshold": 1,
            "QuantityPercent": -1,
            "SpawnAttachments": [],
            "Variants": []
        },
        {
            "ClassName": "ammobox_556x45_20rnd",
            "MaxPriceThreshold": 1000,
            "MinPriceThreshold": 900,
            "SellPricePercent": -1.0,
            "MaxStockThreshold": 1,
            "MinStockThreshold": 1,
            "QuantityPercent": -1,
            "SpawnAttachments": [],
            "Variants": [
                "ammobox_556x45tracer_20rnd"
            ]
        },
        {
            "ClassName": "ammobox_556x45tracer_20rnd",
            "MaxPriceThreshold": 1120,
            "MinPriceThreshold": 1008,
            "SellPricePercent": -1.0,
            "MaxStockThreshold": 1,
            "MinStockThreshold": 1,
            "QuantityPercent": -1,
            "SpawnAttachments": [],
            "Variants": []
        },
        {
            "ClassName": "ammobox_762x39_20rnd",
            "MaxPriceThreshold": 1000,
            "MinPriceThreshold": 900,
            "SellPricePercent": -1.0,
            "MaxStockThreshold": 1,
            "MinStockThreshold": 1,
            "QuantityPercent": -1,
            "SpawnAttachments": [],
            "Variants": [
                "ammobox_762x39tracer_20rnd"
            ]
        },
        {
            "ClassName": "ammobox_762x39tracer_20rnd",
            "MaxPriceThreshold": 1160,
            "MinPriceThreshold": 1044,
            "SellPricePercent": -1.0,
            "MaxStockThreshold": 1,
            "MinStockThreshold": 1,
            "QuantityPercent": -1,
            "SpawnAttachments": [],
            "Variants": []
        },
        {
            "ClassName": "ammobox_762x54_20rnd",
            "MaxPriceThreshold": 1140,
            "MinPriceThreshold": 1026,
            "SellPricePercent": -1.0,
            "MaxStockThreshold": 1,
            "MinStockThreshold": 1,
            "QuantityPercent": -1,
            "SpawnAttachments": [],
            "Variants": [
                "ammobox_762x54tracer_20rnd"
            ]
        },
        {
            "ClassName": "ammobox_762x54tracer_20rnd",
            "MaxPriceThreshold": 1300,
            "MinPriceThreshold": 1170,
            "SellPricePercent": -1.0,
            "MaxStockThreshold": 1,
            "MinStockThreshold": 1,
            "QuantityPercent": -1,
            "SpawnAttachments": [],
            "Variants": []
        },
        {
            "ClassName": "ammobox_9x19_25rnd",
            "MaxPriceThreshold": 575,
            "MinPriceThreshold": 517,
            "SellPricePercent": -1.0,
            "MaxStockThreshold": 1,
            "MinStockThreshold": 1,
            "QuantityPercent": -1,
            "SpawnAttachments": [],
            "Variants": []
        },
        {
            "ClassName": "ammobox_9x39_20rnd",
            "MaxPriceThreshold": 1100,
            "MinPriceThreshold": 72,
            "SellPricePercent": -1.0,
            "MaxStockThreshold": 1,
            "MinStockThreshold": 1,
            "QuantityPercent": -1,
            "SpawnAttachments": [],
            "Variants": [
                "ammobox_9x39ap_20rnd"
            ]
        },
        {
            "ClassName": "ammobox_9x39ap_20rnd",
            "MaxPriceThreshold": 2000,
            "MinPriceThreshold": 1800,
            "SellPricePercent": -1.0,
            "MaxStockThreshold": 1,
            "MinStockThreshold": 1,
            "QuantityPercent": -1,
            "SpawnAttachments": [],
            "Variants": []
        },
        {
            "ClassName": "9x21FOX_AmmoBox_25rnd",
            "MaxPriceThreshold": 625,
            "MinPriceThreshold": 562,
            "SellPricePercent": -1.0,
            "MaxStockThreshold": 1,
            "MinStockThreshold": 1,
            "QuantityPercent": -1,
            "SpawnAttachments": [],
            "Variants": []
          },
          {
            "ClassName": "9x21EXP_AmmoBox_25rnd",
            "MaxPriceThreshold": 875,
            "MinPriceThreshold": 787,
            "SellPricePercent": -1.0,
            "MaxStockThreshold": 1,
            "MinStockThreshold": 1,
            "QuantityPercent": -1,
            "SpawnAttachments": [],
            "Variants": []
          },
          {
            "ClassName": "57x28_AmmoBox_25rnd",
            "MaxPriceThreshold": 750,
            "MinPriceThreshold": 675,
            "SellPricePercent": -1.0,
            "MaxStockThreshold": 1,
            "MinStockThreshold": 1,
            "QuantityPercent": -1,
            "SpawnAttachments": [],
            "Variants": []
          },
          {
            "ClassName": "57x28AP_AmmoBox_25rnd",
            "MaxPriceThreshold": 1500,
            "MinPriceThreshold": 1350,
            "SellPricePercent": -1.0,
            "MaxStockThreshold": 1,
            "MinStockThreshold": 1,
            "QuantityPercent": -1,
            "SpawnAttachments": [],
            "Variants": []
          },
          {
            "ClassName": "TTC_AmmoBox_300blk_20rnd",
            "MaxPriceThreshold": 1000,
            "MinPriceThreshold": 900,
            "SellPricePercent": -1.0,
            "MaxStockThreshold": 1,
            "MinStockThreshold": 1,
            "QuantityPercent": -1,
            "SpawnAttachments": [],
            "Variants": []
        },
        {
            "ClassName": "TTC_AmmoBox_4630_20Rnd",
            "MaxPriceThreshold": 600,
            "MinPriceThreshold": 540,
            "SellPricePercent": -1.0,
            "MaxStockThreshold": 1,
            "MinStockThreshold": 1,
            "QuantityPercent": -1,
            "SpawnAttachments": [],
            "Variants": []
        },
        {
            "ClassName": "TTC_AmmoBox_50AE",
            "MaxPriceThreshold": 1800,
            "MinPriceThreshold": 1620,
            "SellPricePercent": -1.0,
            "MaxStockThreshold": 1,
            "MinStockThreshold": 1,
            "QuantityPercent": -1,
            "SpawnAttachments": [],
            "Variants": []
        },
        {
            "ClassName": "AE_AmmoBox_127x99_10rnd",
            "MaxPriceThreshold": 5000,
            "MinPriceThreshold": 4500,
            "SellPricePercent": -1.0,
            "MaxStockThreshold": 1,
            "MinStockThreshold": 1,
            "QuantityPercent": -1,
            "SpawnAttachments": [],
            "Variants": []
        },
        {
            "ClassName": "BO_AmmoBox_3006_20rnd",
            "MaxPriceThreshold": 2000,
            "MinPriceThreshold": 1800,
            "SellPricePercent": -1.0,
            "MaxStockThreshold": 1,
            "MinStockThreshold": 1,
            "QuantityPercent": -1,
            "SpawnAttachments": [],
            "Variants": []
        },
        {
            "ClassName": "AE_AmmoBox_338_20rnd",
            "MaxPriceThreshold": 4500,
            "MinPriceThreshold": 4050,
            "SellPricePercent": -1.0,
            "MaxStockThreshold": 1,
            "MinStockThreshold": 1,
            "QuantityPercent": -1,
            "SpawnAttachments": [],
            "Variants": []
        },
        {
            "ClassName": "BO_Ammobox_300WinMag_20rnd",
            "MaxPriceThreshold": 4000,
            "MinPriceThreshold": 3600,
            "SellPricePercent": -1.0,
            "MaxStockThreshold": 1,
            "MinStockThreshold": 1,
            "QuantityPercent": -1,
            "SpawnAttachments": [],
            "Variants": []
        },
        {
            "ClassName": "AE_AmmoBox_792x57_20rnd",
            "MaxPriceThreshold": 1200,
            "MinPriceThreshold": 1080,
            "SellPricePercent": -1.0,
            "MaxStockThreshold": 1,
            "MinStockThreshold": 1,
            "QuantityPercent": -1,
            "SpawnAttachments": [],
            "Variants": []
        },
        {
            "ClassName": "792x33fox_AmmoBox_30rnd",
            "MaxPriceThreshold": 1200,
            "MinPriceThreshold": 1080,
            "SellPricePercent": -1.0,
            "MaxStockThreshold": 1,
            "MinStockThreshold": 1,
            "QuantityPercent": -1,
            "SpawnAttachments": [],
            "Variants": []
        }
    ]
}