{
    "m_Version": 12,
    "DisplayName": "#STR_EXPANSION_MARKET_CATEGORY_BACKPACKS",
    "Icon": "Deliver",
    "Color": "FBFCFEFF",
    "IsExchange": 0,
    "InitStockPercent": 50.0,
    "Items": [
        {
            "ClassName": "childbag_red",
            "MaxPriceThreshold": 8000,
            "MinPriceThreshold": 7200,
            "SellPricePercent": -1.0,
            "MaxStockThreshold": 100,
            "MinStockThreshold": 1,
            "QuantityPercent": -1,
            "SpawnAttachments": [],
            "Variants": [
                "childbag_blue",
                "childbag_green"
            ]
        },
        {
            "ClassName": "childbag_green",
            "MaxPriceThreshold": 9000,
            "MinPriceThreshold": 8100,
            "SellPricePercent": -1.0,
            "MaxStockThreshold": 100,
            "MinStockThreshold": 1,
            "QuantityPercent": -1,
            "SpawnAttachments": [],
            "Variants": []
        },
        {
            "ClassName": "drybag_orange",
            "MaxPriceThreshold": 30000,
            "MinPriceThreshold": 27000,
            "SellPricePercent": -1.0,
            "MaxStockThreshold": 100,
            "MinStockThreshold": 1,
            "QuantityPercent": -1,
            "SpawnAttachments": [],
            "Variants": [
                "drybag_yellow",
                "drybag_blue",
                "drybag_black",
                "drybag_red",
                "drybag_green"
            ]
        },
        {
            "ClassName": "drybag_green",
            "MaxPriceThreshold": 32000,
            "MinPriceThreshold": 28000,
            "SellPricePercent": -1.0,
            "MaxStockThreshold": 100,
            "MinStockThreshold": 1,
            "QuantityPercent": -1,
            "SpawnAttachments": [],
            "Variants": []
        },
        {
            "ClassName": "taloonbag_blue",
            "MaxPriceThreshold": 20000,
            "MinPriceThreshold": 18000,
            "SellPricePercent": -1.0,
            "MaxStockThreshold": 100,
            "MinStockThreshold": 1,
            "QuantityPercent": -1,
            "SpawnAttachments": [],
            "Variants": [
                "taloonbag_orange",
                "taloonbag_violet",
                "taloonbag_green"
            ]
        },
        {
            "ClassName": "assaultbag_green",
            "MaxPriceThreshold": 25000,
            "MinPriceThreshold": 22500,
            "SellPricePercent": -1.0,
            "MaxStockThreshold": 100,
            "MinStockThreshold": 1,
            "QuantityPercent": -1,
            "SpawnAttachments": [],
            "Variants": [
                "assaultbag_ttsko",
                "assaultbag_black",
                "assaultbag_winter",
                "MilitaryGear_AssaultBag_PartizanM",
                "MilitaryGear_AssaultBag_Duckhunter",
                "MilitaryGear_AssaultBag_Multicam",
                "MilitaryGear_AssaultBag_Splinter",
                "MilitaryGear_AssaultBag_Splinter_Dark",
                "MilitaryGear_AssaultBag_Tiger",
                "MilitaryGear_AssaultBag_Woodland",
                "MilitaryGear_AssaultBag_FLT",
                "MilitaryGear_AssaultBag_DPM",
                "MilitaryGear_AssaultBag_MPAT",
                "MilitaryGear_AssaultBag_Partizan",
                "MilitaryGear_AssaultBag_Skol",
                "MilitaryGear_AssaultBag_ATACS",
                "MilitaryGear_AssaultBag_CADPAT",
                "MilitaryGear_AssaultBag_Tropic",
                "MilitaryGear_AssaultBag_Yeger"
            ]
        },
        {
            "ClassName": "MilitaryGear_AssaultBag_PartizanM",
            "MaxPriceThreshold": 27500,
            "MinPriceThreshold": 24750,
            "SellPricePercent": -1.0,
            "MaxStockThreshold": 100,
            "MinStockThreshold": 1,
            "QuantityPercent": -1,
            "SpawnAttachments": [],
            "Variants": [
                "MilitaryGear_AssaultBag_Duckhunter",
                "MilitaryGear_AssaultBag_Multicam",
                "MilitaryGear_AssaultBag_Splinter",
                "MilitaryGear_AssaultBag_Splinter_Dark",
                "MilitaryGear_AssaultBag_Tiger",
                "MilitaryGear_AssaultBag_Woodland",
                "MilitaryGear_AssaultBag_FLT",
                "MilitaryGear_AssaultBag_DPM",
                "MilitaryGear_AssaultBag_MPAT",
                "MilitaryGear_AssaultBag_Partizan",
                "MilitaryGear_AssaultBag_Skol",
                "MilitaryGear_AssaultBag_ATACS",
                "MilitaryGear_AssaultBag_CADPAT",
                "MilitaryGear_AssaultBag_Tropic",
                "MilitaryGear_AssaultBag_Yeger"
            ]
        },
        {
            "ClassName": "huntingbag",
            "MaxPriceThreshold": 28000,
            "MinPriceThreshold": 25200,
            "SellPricePercent": -1.0,
            "MaxStockThreshold": 100,
            "MinStockThreshold": 1,
            "QuantityPercent": -1,
            "SpawnAttachments": [],
            "Variants": [
                "huntingbag_Hannah",
                "MilitaryGear_HuntingBag_PartizanM",
                "MilitaryGear_HuntingBag_Duckhunter",
                "MilitaryGear_HuntingBag_Multicam",
                "MilitaryGear_HuntingBag_Splinter",
                "MilitaryGear_HuntingBag_Splinter_Dark",
                "MilitaryGear_HuntingBag_Tiger",
                "MilitaryGear_HuntingBag_Woodland",
                "MilitaryGear_HuntingBag_FLT",
                "MilitaryGear_HuntingBag_DPM",
                "MilitaryGear_HuntingBag_MPAT",
                "MilitaryGear_HuntingBag_Partizan",
                "MilitaryGear_HuntingBag_Skol",
                "MilitaryGear_HuntingBag_ATACS",
                "MilitaryGear_HuntingBag_CADPAT",
                "MilitaryGear_HuntingBag_Tropic",
                "MilitaryGear_HuntingBag_Yeger"
            ]
        },
        {
            "ClassName": "tortillabag",
            "MaxPriceThreshold": 37333,
            "MinPriceThreshold": 33600,
            "SellPricePercent": -1.0,
            "MaxStockThreshold": 100,
            "MinStockThreshold": 1,
            "QuantityPercent": -1,
            "SpawnAttachments": [],
            "Variants": [
                "TortillaBag_Winter",
                "expansiondeserttortilla",
                "MilitaryGear_TortillaBag_PartizanM",
                "MilitaryGear_TortillaBag_Duckhunter",
                "MilitaryGear_TortillaBag_Multicam",
                "MilitaryGear_TortillaBag_Splinter",
                "MilitaryGear_TortillaBag_Splinter_Dark",
                "MilitaryGear_TortillaBag_Tiger",
                "MilitaryGear_TortillaBag_Woodland",
                "MilitaryGear_TortillaBag_FLT",
                "MilitaryGear_TortillaBag_DPM",
                "MilitaryGear_TortillaBag_MPAT",
                "MilitaryGear_TortillaBag_Partizan",
                "MilitaryGear_TortillaBag_Skol",
                "MilitaryGear_TortillaBag_ATACS",
                "MilitaryGear_TortillaBag_CADPAT",
                "MilitaryGear_TortillaBag_Tropic",
                "MilitaryGear_TortillaBag_Yeger"
            ]
        },
        {
            "ClassName": "coyotebag_brown",
            "MaxPriceThreshold": 37333,
            "MinPriceThreshold": 33600,
            "SellPricePercent": -1.0,
            "MaxStockThreshold": 100,
            "MinStockThreshold": 1,
            "QuantityPercent": -1,
            "SpawnAttachments": [],
            "Variants": [
                "coyotebag_green",
                "expansioncoyoteblack",
                "MilitaryGear_CoyoteBag_PartizanM",
                "MilitaryGear_CoyoteBag_Duckhunter",
                "MilitaryGear_CoyoteBag_Multicam",
                "MilitaryGear_CoyoteBag_Splinter",
                "MilitaryGear_CoyoteBag_Splinter_Dark",
                "MilitaryGear_CoyoteBag_Tiger",
                "MilitaryGear_CoyoteBag_Woodland",
                "MilitaryGear_CoyoteBag_FLT",
                "MilitaryGear_CoyoteBag_DPM",
                "MilitaryGear_CoyoteBag_MPAT",
                "MilitaryGear_CoyoteBag_Partizan",
                "MilitaryGear_CoyoteBag_Skol",
                "MilitaryGear_CoyoteBag_ATACS",
                "MilitaryGear_CoyoteBag_CADPAT",
                "MilitaryGear_CoyoteBag_Tropic",
                "MilitaryGear_CoyoteBag_Yeger"
            ]
        },
        {
            "ClassName": "mountainbag_red",
            "MaxPriceThreshold": 37333,
            "MinPriceThreshold": 33600,
            "SellPricePercent": -1.0,
            "MaxStockThreshold": 100,
            "MinStockThreshold": 1,
            "QuantityPercent": -1,
            "SpawnAttachments": [],
            "Variants": [
                "mountainbag_blue",
                "mountainbag_orange",
                "mountainbag_green",
                "MilitaryGear_MountainBag_PartizanM",
                "MilitaryGear_MountainBag_Duckhunter",
                "MilitaryGear_MountainBag_Multicam",
                "MilitaryGear_MountainBag_Splinter",
                "MilitaryGear_MountainBag_Splinter_Dark",
                "MilitaryGear_MountainBag_Tiger",
                "MilitaryGear_MountainBag_Woodland",
                "MilitaryGear_MountainBag_FLT",
                "MilitaryGear_MountainBag_DPM",
                "MilitaryGear_MountainBag_MPAT",
                "MilitaryGear_MountainBag_Partizan",
                "MilitaryGear_MountainBag_Skol",
                "MilitaryGear_MountainBag_ATACS",
                "MilitaryGear_MountainBag_CADPAT",
                "MilitaryGear_MountainBag_Tropic",
                "MilitaryGear_MountainBag_Yeger"
            ]
        },
        {
            "ClassName": "alicebag_green",
            "MaxPriceThreshold": 45000,
            "MinPriceThreshold": 40500,
            "SellPricePercent": -1.0,
            "MaxStockThreshold": 100,
            "MinStockThreshold": 1,
            "QuantityPercent": -1,
            "SpawnAttachments": [],
            "Variants": [
                "alicebag_black",
                "alicebag_camo",
                "MilitaryGear_AliceBag_PartizanM",
                "MilitaryGear_AliceBag_Duckhunter",
                "MilitaryGear_AliceBag_Multicam",
                "MilitaryGear_AliceBag_Splinter",
                "MilitaryGear_AliceBag_Splinter_Dark",
                "MilitaryGear_AliceBag_Tiger",
                "MilitaryGear_AliceBag_Woodland",
                "MilitaryGear_AliceBag_FLT",
                "MilitaryGear_AliceBag_DPM",
                "MilitaryGear_AliceBag_MPAT",
                "MilitaryGear_AliceBag_Partizan",
                "MilitaryGear_AliceBag_Skol",
                "MilitaryGear_AliceBag_ATACS",
                "MilitaryGear_AliceBag_CADPAT",
                "MilitaryGear_AliceBag_Tropic",
                "MilitaryGear_AliceBag_Yeger"
            ]
        },
        {
            "ClassName": "FOG_Bag_6ShBagT_Black",
            "MaxPriceThreshold": 120000,
            "MinPriceThreshold": 108000,
            "SellPricePercent": -1.0,
            "MaxStockThreshold": 100,
            "MinStockThreshold": 1,
            "QuantityPercent": -1,
            "SpawnAttachments": [],
            "Variants": [
                "FOG_Bag_6ShBagT_Green",
                "FOG_Bag_6ShBagT_RG",
                "FOG_Bag_6ShBagT_CB",
                "FOG_Bag_6ShBagT_BlackEMR",
                "FOG_Bag_6ShBagT_White",
                "FOG_Bag_6ShBagT_EMR_White"
            ]
        },
        {
            "ClassName": "FOG_Bag_CommsBag_Tan",
            "MaxPriceThreshold": 60000,
            "MinPriceThreshold": 54000,
            "SellPricePercent": -1.0,
            "MaxStockThreshold": 100,
            "MinStockThreshold": 1,
            "QuantityPercent": -1,
            "SpawnAttachments": [],
            "Variants": [
                "FOG_Bag_CommsBag_CB",
                "FOG_Bag_CommsBag_RG",
                "FOG_Bag_CommsBag_Black",
                "FOG_Bag_CommsBag_White",
                "FOG_Bag_CommsBag_MC",
                "FOG_Bag_CommsBag_MCAL",
                "FOG_Bag_CommsBag_MCB",
                "FOG_Bag_CommsBag_MCT",
                "FOG_Bag_CommsBag_M81"
            ]
        },
        {
            "ClassName": "FOG_Bergen_Rucksack_Black",
            "MaxPriceThreshold": 73333,
            "MinPriceThreshold": 66000,
            "SellPricePercent": -1.0,
            "MaxStockThreshold": 100,
            "MinStockThreshold": 1,
            "QuantityPercent": -1,
            "SpawnAttachments": [],
            "Variants": [
                "FOG_Bergen_Rucksack_Green",
                "FOG_Bergen_Rucksack_Woodland",
                "FOG_Bergen_Rucksack_Multicam",
                "FOG_Bergen_Rucksack_ERDL"
            ]
        },
        {
            "ClassName": "FOG_Bag_DrawBridge_Black",
            "MaxPriceThreshold": 60000,
            "MinPriceThreshold": 54000,
            "SellPricePercent": -1.0,
            "MaxStockThreshold": 100,
            "MinStockThreshold": 1,
            "QuantityPercent": -1,
            "SpawnAttachments": [],
            "Variants": [
                "FOG_Bag_DrawBridge_CB",
                "FOG_Bag_DrawBridge_RG",
                "FOG_Bag_DrawBridge_OD",
                "FOG_Bag_DrawBridge_Tan",
                "FOG_Bag_DrawBridge_Grey",
                "FOG_Bag_DrawBridge_MC",
                "FOG_Bag_DrawBridge_MCAL",
                "FOG_Bag_DrawBridge_MCB",
                "FOG_Bag_DrawBridge_White"
            ]
        },
        {
            "ClassName": "FOG_Bag_SATL_MC",
            "MaxPriceThreshold": 140000,
            "MinPriceThreshold": 126000,
            "SellPricePercent": -1.0,
            "MaxStockThreshold": 100,
            "MinStockThreshold": 1,
            "QuantityPercent": -1,
            "SpawnAttachments": [],
            "Variants": [
                "FOG_Bag_SATL_RG",
                "FOG_Bag_SATL_CB",
                "FOG_Bag_SATL_KHK",
                "FOG_Bag_SATL_Black",
                "FOG_Bag_SATL_Grey"
            ]
        },
        {
            "ClassName": "FOG_Bag_F4Terminator",
            "MaxPriceThreshold": 86666,
            "MinPriceThreshold": 77999,
            "SellPricePercent": -1.0,
            "MaxStockThreshold": 100,
            "MinStockThreshold": 1,
            "QuantityPercent": -1,
            "SpawnAttachments": [],
            "Variants": [
                "FOG_Bag_F4Terminator_BlackTiger",
                "FOG_Bag_F4Terminator_Black",
                "FOG_Bag_F4Terminator_RG",
                "FOG_Bag_F4Terminator_CB",
                "FOG_Bag_F4Terminator_OD"
            ]
        },
        {
            "ClassName": "FOG_Bag_MRASAP_Black",
            "MaxPriceThreshold": 46666,
            "MinPriceThreshold": 41999,
            "SellPricePercent": -1.0,
            "MaxStockThreshold": 100,
            "MinStockThreshold": 1,
            "QuantityPercent": -1,
            "SpawnAttachments": [],
            "Variants": [
                "FOG_Bag_MRASAP_Grey",
                "FOG_Bag_MRASAP_RG",
                "FOG_Bag_MRASAP_CB",
                "FOG_Bag_MRASAP_MC"
            ]
        },
        {
            "ClassName": "FOG_Bag_BlackJack_Black",
            "MaxPriceThreshold": 120000,
            "MinPriceThreshold": 108000,
            "SellPricePercent": -1.0,
            "MaxStockThreshold": 100,
            "MinStockThreshold": 1,
            "QuantityPercent": -1,
            "SpawnAttachments": [],
            "Variants": [
                "FOG_Bag_BlackJack_MC",
                "FOG_Bag_BlackJack_RG",
                "FOG_Bag_BlackJack_CB",
                "FOG_Bag_BlackJack_MCB",
                "FOG_Bag_BlackJack_ERDL",
                "FOG_Bag_BlackJack_MCT",
                "FOG_Bag_BlackJack_MCAL",
                "FOG_Bag_BlackJack_OD",
                "FOG_Bag_BlackJack_KHK"
            ]
        },
        {
            "ClassName": "FOG_Bag_SSO_Black",
            "MaxPriceThreshold": 66666,
            "MinPriceThreshold": 60000,
            "SellPricePercent": -1.0,
            "MaxStockThreshold": 100,
            "MinStockThreshold": 1,
            "QuantityPercent": -1,
            "SpawnAttachments": [],
            "Variants": [
                "FOG_Bag_SSO_Tan",
                "FOG_Bag_SSO_MC",
                "FOG_Bag_SSO_CB",
                "FOG_Bag_SSO_MCB",
                "FOG_Bag_SSO_Toxic"
            ]
        },
        {
            "ClassName": "FOG_Bag_Trizip_Black",
            "MaxPriceThreshold": 40000,
            "MinPriceThreshold": 36000,
            "SellPricePercent": -1.0,
            "MaxStockThreshold": 100,
            "MinStockThreshold": 1,
            "QuantityPercent": -1,
            "SpawnAttachments": [],
            "Variants": [
                "FOG_Bag_Trizip_Puke",
                "FOG_Bag_Trizip_RG",
                "FOG_Bag_Trizip_CB",
                "FOG_Bag_Trizip_RGCB",
                "FOG_Bag_Trizip_MARPAT",
                "FOG_Bag_Trizip_ATACSFG",
                "FOG_Bag_Trizip_DCU",
                "FOG_Bag_Trizip_ERDL",
                "FOG_Bag_Trizip_MC"
            ]
        },
        {
            "ClassName": "SurvivorBackpack_Green",
            "MaxPriceThreshold": 13000,
            "MinPriceThreshold": 11700,
            "SellPricePercent": -1.0,
            "MaxStockThreshold": 100,
            "MinStockThreshold": 1,
            "QuantityPercent": -1,
            "SpawnAttachments": [],
            "Variants": [
                "SurvivorBackpack_Black",
                "SurvivorBackpack_Blue",
                "SurvivorBackpack_Pink",
                "SurvivorBackpack_Red",
                "SurvivorBackpack_Yellow"
            ]
        },
        {
            "ClassName": "Canvas_Backpack_Base",
            "MaxPriceThreshold": 40000,
            "MinPriceThreshold": 36000,
            "SellPricePercent": -1.0,
            "MaxStockThreshold": 100,
            "MinStockThreshold": 1,
            "QuantityPercent": -1,
            "SpawnAttachments": [],
            "Variants": [
                "Canvas_Backpack_Black",
                "Canvas_Backpack_White",
                "Canvas_Backpack_Red",
                "Canvas_Backpack_Blue",
                "Canvas_Backpack_Purple"
            ]
        },
        {
            "ClassName": "Msp_SlingBackpack_Black",
            "MaxPriceThreshold": 30000,
            "MinPriceThreshold": 27000,
            "SellPricePercent": -1.0,
            "MaxStockThreshold": 100,
            "MinStockThreshold": 1,
            "QuantityPercent": -1,
            "SpawnAttachments": [],
            "Variants": [
                "Msp_SlingBackpack_Green",
                "Msp_SlingBackpack_Gray",
                "Msp_SlingBackpack_Tan"
            ]
        },
        {
            "ClassName": "FC_Fish_Bag",
            "MaxPriceThreshold": 70000,
            "MinPriceThreshold": 63000,
            "SellPricePercent": -1.0,
            "MaxStockThreshold": 100,
            "MinStockThreshold": 1,
            "QuantityPercent": -1,
            "SpawnAttachments": [],
            "Variants": [
                "FC_Fish_Bag_Black",
                "FC_Fish_Bag_Green"
            ]
        },
        {
            "ClassName": "FC_Fish_Bag_Black",
            "MaxPriceThreshold": 72000,
            "MinPriceThreshold": 64800,
            "SellPricePercent": -1.0,
            "MaxStockThreshold": 100,
            "MinStockThreshold": 1,
            "QuantityPercent": -1,
            "SpawnAttachments": [],
            "Variants": []
        },
        {
            "ClassName": "FC_Fish_Bag_Green",
            "MaxPriceThreshold": 72000,
            "MinPriceThreshold": 64800,
            "SellPricePercent": -1.0,
            "MaxStockThreshold": 100,
            "MinStockThreshold": 1,
            "QuantityPercent": -1,
            "SpawnAttachments": [],
            "Variants": []
        },
        {
            "ClassName": "Nomadbackpack_v3_BaseColor",
            "MaxPriceThreshold": 180000,
            "MinPriceThreshold": 162000,
            "SellPricePercent": -1.0,
            "MaxStockThreshold": 100,
            "MinStockThreshold": 1,
            "QuantityPercent": -1,
            "SpawnAttachments": [],
            "Variants": [
                "Nomadbackpack_v3_Blue",
                "Nomadbackpack_v3_Teal",
                "Nomadbackpack_v3_Green",
                "Nomadbackpack_v3_Grey",
                "Nomadbackpack_v3_Red",
                "Nomadbackpack_v3_Yellow",
                "Nomadbackpack_v3_Black",
                "Nomadbackpack_v3_AoR2",
                "Nomadbackpack_v3_Woodland",
                "Nomadbackpack_v3_Winter"
            ]
        }
    ]
}